[{"url":"http://www.cdlr.gov.cn/detailnoright.aspx?id=118434","title":"成都市拍卖出让国有建设用地使用权公告(成公资土拍告[2018]26号)","date":"2018-06-08","code":"TF(05/07):2018-14","address":"天府新区正兴街道秦皇寺村五组（天府中心范围内，宁波路以北，杭州路以南）","area":"24363.65\n\n合36.5455亩","areaTrans":"24363.65","type":"商服用地、住宅用地\n\n商服用地40年住宅用地70年","startPrice":"480万元/亩","startPriceTrans":"7207.21","img":"http://www.cdggzy.com:8080/ueditor/netfile/upload/2018-06-08/897bd239-b900-48bd-bc07-9f77d44df1d2.jpg","localImg":"897bd239-b900-48bd-bc07-9f77d44df1d2.jpg"},{"url":"http://www.cdlr.gov.cn/detailnoright.aspx?id=118433","title":"成都市挂牌出让国有建设用地使用权公告(成公资土挂告[2018]31号)","date":"2018-06-08","code":"DJY2018-02(05)","address":"都江堰市青城山镇桃花社区","area":"50683.71\n\n合76.0256亩","areaTrans":"50683.71","type":"商服用地\n\n40年","startPrice":"90万元/亩","startPriceTrans":"1351.35","img":"http://www.cdggzy.com:8080/ueditor/netfile/upload/2018-06-08/367aa013-6e94-4909-baec-e0e11a430a80.jpg","localImg":"367aa013-6e94-4909-baec-e0e11a430a80.jpg"},{"url":"http://www.cdlr.gov.cn/detailnoright.aspx?id=118343","title":"成都市挂牌出让国有建设用地使用权公告(成公资土挂告[2018]29号)","date":"2018-06-07","code":"GX2018-07（05）","address":"高新区中和街道应龙社区7组（原陆肖村2、3社），应龙社区8组（原陆肖村4、5社）","area":"44356.90\n\n合66.5354亩","areaTrans":"44356.90","type":"商服用地\n\n40年","startPrice":"楼面地价：2819元/平方米\n\n ","startPriceTrans":"2819","img":"http://www.cdggzy.com:8080/ueditor/netfile/upload/2018-06-07/621773b0-627d-4529-8625-48c3a39a93ec.jpg","localImg":"621773b0-627d-4529-8625-48c3a39a93ec.jpg"},{"url":"http://www.cdlr.gov.cn/detailnoright.aspx?id=118343","title":"成都市挂牌出让国有建设用地使用权公告(成公资土挂告[2018]29号)","date":"2018-06-07","code":"WH04（21）：2018-014","address":"武侯区簇锦街道办事处铁佛村4、5、6、8组","area":"30243.90\n\n合45.3658亩","areaTrans":"30243.90","type":"商服用地\n\n商业用地40年","startPrice":"楼面地价：2850元/平方米\n\n ","startPriceTrans":"2850","img":"http://www.cdggzy.com:8080/ueditor/netfile/upload/2018-06-07/83608a85-1c20-43c5-aba9-840cca8a3a2b.jpg","localImg":"83608a85-1c20-43c5-aba9-840cca8a3a2b.jpg"},{"url":"http://www.cdlr.gov.cn/detailnoright.aspx?id=118196","title":"成都市拍卖出让国有建设用地使用权公告(成公资土拍告[2018]25号)","date":"2018-06-06","code":"GX2018-08（071）","address":"高新区桂溪街道临江村六、七、八组","area":"25364.86\n\n合38.0473亩","areaTrans":"25364.86","type":"住宅用地\n\n住宅70年","startPrice":"楼面地价：10100元/平方米\n\n ","startPriceTrans":"10100","img":"http://www.cdggzy.com:8080/ueditor/netfile/upload/2018-06-06/42940e50-b6c6-44df-aa9a-691f1b56d838.jpg","localImg":"42940e50-b6c6-44df-aa9a-691f1b56d838.jpg"},{"url":"http://www.cdlr.gov.cn/detailnoright.aspx?id=118196","title":"成都市拍卖出让国有建设用地使用权公告(成公资土拍告[2018]25号)","date":"2018-06-06","code":"GX2018-09（071）","address":"高新区中和街道应龙社区一组(原张家寺村一社)、应龙社区三组(原张家寺村四社)","area":"84423.42\n\n合126.6351亩","areaTrans":"84423.42","type":"住宅用地\n\n住宅70年","startPrice":"楼面地价：9240元/平方米\n\n ","startPriceTrans":"9240","img":"http://www.cdggzy.com:8080/ueditor/netfile/upload/2018-06-06/c6298970-cd13-4efd-a1e9-a5ab7fefc6aa.jpg","localImg":"c6298970-cd13-4efd-a1e9-a5ab7fefc6aa.jpg"},{"url":"http://www.cdlr.gov.cn/detailnoright.aspx?id=117852","title":"成都市挂牌出让国有建设用地使用权公告(成公资土挂告[2018]28号)","date":"2018-06-04","code":"JT2018-04(211)","address":"金堂县学府大道连接线东侧、金堂大道南侧（西南航空学院北侧地块一）","area":"98715.28\n\n合148.07亩","areaTrans":"98715.28","type":"商服用地\n\n商服40年","startPrice":"80万元/亩","startPriceTrans":"1201.20","img":"http://www.cdggzy.com:8080/ueditor/netfile/upload/2018-06-04/d7e6f760-ca87-49bf-a21a-4bb587f52012.jpg","localImg":"d7e6f760-ca87-49bf-a21a-4bb587f52012.jpg"},{"url":"http://www.cdlr.gov.cn/detailnoright.aspx?id=117852","title":"成都市挂牌出让国有建设用地使用权公告(成公资土挂告[2018]28号)","date":"2018-06-04","code":"JT2018-05(211)","address":"金堂县金堂大道南侧（西南航空学院北侧地块二）","area":"22513.72\n\n合33.77亩","areaTrans":"22513.72","type":"商服用地\n\n商服40年","startPrice":"80万元/亩","startPriceTrans":"1201.20","localImg":""},{"url":"http://www.cdlr.gov.cn/detailnoright.aspx?id=117850","title":"成都市挂牌出让国有建设用地使用权公告(成公资土网挂告[2018]27号)","date":"2018-06-04","code":"GX2018-10(061)","address":"高新区西区（郫都区）德源镇回龙村2、4、5、6、7、8社","area":"422567.43\n\n合633.8511亩","areaTrans":"422567.43","type":"工业用地\n\n50年","startPrice":"22万元/亩","startPriceTrans":"330.33","img":"http://www.cdggzy.com:8080/ueditor/netfile/upload/2018-06-04/ab801365-88ed-49af-b426-fe155d76f938.jpg","localImg":"ab801365-88ed-49af-b426-fe155d76f938.jpg"},{"url":"http://www.cdlr.gov.cn/detailnoright.aspx?id=117547","title":"成都市拍卖出让国有建设用地使用权公告(成公资土拍告[2018]24号)","date":"2018-05-30","code":"LQ08(252):2018-08","address":"龙泉驿区洛带镇江西堰街以东、闽西路以北","area":"25914.76\n\n合38.8721亩","areaTrans":"25914.76","type":"住宅用地\n\n70年","startPrice":"楼面地价：6000元/平方米\n\n ","startPriceTrans":"6000","img":"http://www.cdggzy.com:8080/ueditor/netfile/upload/2018-05-30/23eccc9a-76f8-4029-b2b0-9070782c28ec.jpg","localImg":"23eccc9a-76f8-4029-b2b0-9070782c28ec.jpg"},{"url":"http://www.cdlr.gov.cn/detailnoright.aspx?id=117547","title":"成都市拍卖出让国有建设用地使用权公告(成公资土拍告[2018]24号)","date":"2018-05-30","code":"LQ07(252):2018-07","address":"龙泉驿区洛带镇洛霞路以东、赣南路以北","area":"45867.29\n\n合68.8009亩","areaTrans":"45867.29","type":"住宅用地\n\n70年","startPrice":"楼面地价：6000元/平方米\n\n ","startPriceTrans":"6000","localImg":""},{"url":"http://www.cdlr.gov.cn/detailnoright.aspx?id=117546","title":"成都市挂牌出让国有建设用地使用权公告(成公资土挂告[2018]26号)","date":"2018-05-30","code":"SLG—（05）— 2018—003","address":"双流区西航港街道星月社区集体（实际为星月社区1、7组）、寺圣社区集体（实际为湖夹滩社区1组）","area":"53184.61\n\n合79.7769亩","areaTrans":"53184.61","type":"商服用地\n\n商服用地40年","startPrice":"楼面地价：1640元/平方米\n\n ","startPriceTrans":"1640","img":"http://www.cdggzy.com:8080/ueditor/netfile/upload/2018-05-30/01bc2d95-bf35-4ffe-9c59-089d4bd3adef.jpg","localImg":"01bc2d95-bf35-4ffe-9c59-089d4bd3adef.jpg"},{"url":"http://www.cdlr.gov.cn/detailnoright.aspx?id=116901","title":"成都市拍卖出让国有建设用地使用权公告(成公资土拍告[2018]23号)","date":"2018-05-23","code":"TF(07/05):2018-10","address":"天府新区万安街道高饭店村二、三组（天府新城范围内，梓州大道东侧，武汉路北侧）","area":"81658.73\n\n合122.4881亩(其中出让面积 117.0779亩)","areaTrans":"81658.73","type":"住宅用地、商服用地\n\n住宅用地70年、商服用地40年","startPrice":"960万元/亩","startPriceTrans":"14414.41","img":"http://www.cdggzy.com:8080/ueditor/netfile/upload/2018-05-23/fc64599d-88dc-4f45-a572-a33940bca593.jpg","localImg":"fc64599d-88dc-4f45-a572-a33940bca593.jpg"},{"url":"http://www.cdlr.gov.cn/detailnoright.aspx?id=116901","title":"成都市拍卖出让国有建设用地使用权公告(成公资土拍告[2018]23号)","date":"2018-05-23","code":"PD2018-01","address":"郫都区德源镇清江村二社、五社","area":"114641.75\n\n合171.9626亩(其中出让面积 107.6103亩)","areaTrans":"114641.75","type":"住宅用地\n\n住宅用地70年","startPrice":"楼面地价：3600元/平方米\n\n ","startPriceTrans":"3600","img":"http://www.cdggzy.com:8080/ueditor/netfile/upload/2018-05-23/4cbc3f4d-b5de-47df-914e-03f88b9d3375.jpg","localImg":"4cbc3f4d-b5de-47df-914e-03f88b9d3375.jpg"},{"url":"http://www.cdlr.gov.cn/detailnoright.aspx?id=116901","title":"成都市拍卖出让国有建设用地使用权公告(成公资土拍告[2018]23号)","date":"2018-05-23","code":"PD2018-02","address":"郫都区德源镇清江村二社、三社、花石村一社","area":"39579.84\n\n合59.3698亩(其中出让面积 33.9714亩)","areaTrans":"39579.84","type":"住宅、商业用地\n\n住宅用地70年、商业用地40年","startPrice":"楼面地价：2866元/平方米\n\n ","startPriceTrans":"2866","img":"http://www.cdggzy.com:8080/ueditor/netfile/upload/2018-05-23/f628fafe-8ab3-4244-a275-0a9705bdcecf.jpg","localImg":"f628fafe-8ab3-4244-a275-0a9705bdcecf.jpg"},{"url":"http://www.cdlr.gov.cn/detailnoright.aspx?id=116620","title":"成都市挂牌出让国有建设用地使用权公告(成公资土挂告[2018]25号)","date":"2018-05-21","code":"SLG—（05）— 2018—002","address":"双流区协和街道红瓦社区4、6组","area":"9997.16\n\n合14.9957亩","areaTrans":"9997.16","type":"商服用地\n\n商服用地40年","startPrice":"楼面地价：1120元/平方米\n\n ","startPriceTrans":"1120","img":"http://www.cdggzy.com:8080/ueditor/netfile/upload/2018-05-21/2ebd3b8b-a78e-43e7-947c-00f461e393c8.jpg","localImg":"2ebd3b8b-a78e-43e7-947c-00f461e393c8.jpg"},{"url":"http://www.cdlr.gov.cn/detailnoright.aspx?id=116620","title":"成都市挂牌出让国有建设用地使用权公告(成公资土挂告[2018]25号)","date":"2018-05-21","code":"DJY2018-05(05)","address":"都江堰市向峨乡莲月社区、茶房社区","area":"34878.12\n\n合52.3172亩","areaTrans":"34878.12","type":"商服用地\n\n40年","startPrice":"32万元/亩","startPriceTrans":"480.48","img":"http://www.cdggzy.com:8080/ueditor/netfile/upload/2018-05-21/51a1d162-20c1-4e2b-ac8d-2a8b6a4124a6.jpg","localImg":"51a1d162-20c1-4e2b-ac8d-2a8b6a4124a6.jpg"},{"url":"http://www.cdlr.gov.cn/detailnoright.aspx?id=116618","title":"成都市拍卖出让国有建设用地使用权公告(成公资土拍告[2018]22号)","date":"2018-05-21","code":"SLG-（07/05）-2018-001","address":"双流区公兴街道藕塘社区1、3组，草坪社区1组","area":"41877.33\n\n合62.8160亩","areaTrans":"41877.33","type":"城镇住宅兼容商服用地\n\n住宅用地70年商业用地40年","startPrice":"楼面地价：7000元/平方米\n\n ","startPriceTrans":"7000","img":"http://www.cdggzy.com:8080/ueditor/netfile/upload/2018-05-21/73dfd0d0-1397-44d8-a995-e5fe8ec14c91.jpg","localImg":"73dfd0d0-1397-44d8-a995-e5fe8ec14c91.jpg"},{"url":"http://www.cdlr.gov.cn/detailnoright.aspx?id=116618","title":"成都市拍卖出让国有建设用地使用权公告(成公资土拍告[2018]22号)","date":"2018-05-21","code":"SLG—（07/05）— 2018—002","address":"双流区东升街道清泰社区1组、紫东阁社区集体（原清泰社区1组）","area":"18460.96\n\n合27.6914亩","areaTrans":"18460.96","type":"城镇住宅兼容商服用地\n\n住宅用地70年商业用地40年","startPrice":"楼面地价：6706元/平方米\n\n ","startPriceTrans":"6706","img":"http://www.cdggzy.com:8080/ueditor/netfile/upload/2018-05-21/9a528c17-cc06-4cd0-b712-2039236603f4.jpg","localImg":"9a528c17-cc06-4cd0-b712-2039236603f4.jpg"},{"url":"http://www.cdlr.gov.cn/detailnoright.aspx?id=116618","title":"成都市拍卖出让国有建设用地使用权公告(成公资土拍告[2018]22号)","date":"2018-05-21","code":"LQ02(252):2018-02","address":"龙泉驿区十陵街道长灵南路以东、江月东路以北","area":"26666.67\n\n合40亩","areaTrans":"26666.67","type":"住宅用地\n\n70年","startPrice":"楼面地价：9200元/平方米\n\n ","startPriceTrans":"9200","img":"http://www.cdggzy.com:8080/ueditor/netfile/upload/2018-05-21/fb8aa51d-73b5-41b3-bf45-436571e21225.jpg","localImg":"fb8aa51d-73b5-41b3-bf45-436571e21225.jpg"},{"url":"http://www.cdlr.gov.cn/detailnoright.aspx?id=116203","title":"成都市拍卖出让国有建设用地使用权公告(成公资土拍告[2018]21号)","date":"2018-05-16","code":"PD2017-19（犀浦X3地块）","address":"郫都区犀浦镇万福村四社、梓潼村四社、龙吟村5组","area":"50553.41\n\n合75.8301亩(其中出让面积 36.9529亩)","areaTrans":"50553.41","type":"二类住宅用地\n\n住宅70年","startPrice":"楼面地价：7200元/平方米\n\n ","startPriceTrans":"7200","img":"http://www.cdggzy.com:8080/ueditor/netfile/upload/2018-05-16/685432d4-9c7f-4aaa-8d70-7e4183e7c505.jpg","localImg":"685432d4-9c7f-4aaa-8d70-7e4183e7c505.jpg"},{"url":"http://www.cdlr.gov.cn/detailnoright.aspx?id=116203","title":"成都市拍卖出让国有建设用地使用权公告(成公资土拍告[2018]21号)","date":"2018-05-16","code":"DJY2017-09（252/21）","address":"都江堰市奎光塔街道滨河社区","area":"26392.68\n\n合39.5890亩","areaTrans":"26392.68","type":"城镇混合住宅用地\n\n住宅70年商服40年","startPrice":"350万元/亩","startPriceTrans":"5255.26","img":"http://www.cdggzy.com:8080/ueditor/netfile/upload/2018-05-16/365061ac-f2a5-4791-af20-45df73015f0f.jpg","localImg":"365061ac-f2a5-4791-af20-45df73015f0f.jpg"},{"url":"http://www.cdlr.gov.cn/detailnoright.aspx?id=116203","title":"成都市拍卖出让国有建设用地使用权公告(成公资土拍告[2018]21号)","date":"2018-05-16","code":"DJY2017-10（252/21）","address":"都江堰市奎光塔街道滨河社区","area":"39064\n\n合58.5960亩","areaTrans":"39064","type":"城镇混合住宅用地\n\n住宅70年商服40年","startPrice":"350万元/亩","startPriceTrans":"5255.26","img":"http://www.cdggzy.com:8080/ueditor/netfile/upload/2018-05-16/ec237da9-2358-4540-9c5c-d734497d979b.jpg","localImg":"ec237da9-2358-4540-9c5c-d734497d979b.jpg"},{"url":"http://www.cdlr.gov.cn/detailnoright.aspx?id=116075","title":"成都市挂牌出让国有建设用地使用权公告(成公资土挂告[2018]24号)","date":"2018-05-15","code":"QBJG2018-3（211）号","address":"青白江区凤凰路以东、凤祥大道以南","area":"68723.19\n\n合103.0848亩","areaTrans":"68723.19","type":"商业用地\n\n40年","startPrice":"楼面地价：2000元/平方米\n\n ","startPriceTrans":"2000","img":"http://www.cdggzy.com:8080/ueditor/netfile/upload/2018-05-15/9b12126c-3fcf-4642-8ff4-a34e5c2d70cb.jpg","localImg":"9b12126c-3fcf-4642-8ff4-a34e5c2d70cb.jpg"},{"url":"http://www.cdlr.gov.cn/detailnoright.aspx?id=116074","title":"成都市挂牌出让国有建设用地使用权公告(成公资土挂告[2018]24号)","date":"2018-05-15","code":"QBJG2018-3（211）号","address":"青白江区凤凰路以东、凤祥大道以南","area":"68723.19\n\n合103.0848亩","areaTrans":"68723.19","type":"商业用地\n\n40年","startPrice":"楼面地价：2000元/平方米\n\n ","startPriceTrans":"2000","img":"http://www.cdggzy.com:8080/ueditor/netfile/upload/2018-05-15/9b12126c-3fcf-4642-8ff4-a34e5c2d70cb.jpg","localImg":"9b12126c-3fcf-4642-8ff4-a34e5c2d70cb.jpg"},{"url":"http://www.cdlr.gov.cn/detailnoright.aspx?id=115709","title":"成都市挂牌出让国有建设用地使用权公告(成公资土挂告[2018]23号)","date":"2018-05-10","code":"QBJG2018-1（211）号","address":"青白江区凤凰大道二段以南、凤凰西六路以东","area":"44989.37\n\n合67.4841亩","areaTrans":"44989.37","type":"商业用地\n\n40年","startPrice":"楼面地价：600元/平方米\n\n ","startPriceTrans":"600","img":"http://www.cdggzy.com:8080/ueditor/netfile/upload/2018-05-10/f93b6dd9-8f70-4ba3-bf6e-4da7db8e2ce2.jpg","localImg":"f93b6dd9-8f70-4ba3-bf6e-4da7db8e2ce2.jpg"},{"url":"http://www.cdlr.gov.cn/detailnoright.aspx?id=115709","title":"成都市挂牌出让国有建设用地使用权公告(成公资土挂告[2018]23号)","date":"2018-05-10","code":"QBJG2018-2（211）号","address":"青白江区凤凰大道以南、凤凰西六路以西","area":"26986.38\n\n合40.4796亩","areaTrans":"26986.38","type":"商业用地\n\n40年","startPrice":"楼面地价：600元/平方米\n\n ","startPriceTrans":"600","localImg":""},{"url":"http://www.cdlr.gov.cn/detailnoright.aspx?id=115615","title":"成都市拍卖出让国有建设用地使用权公告(成公资土拍告[2018]20号)","date":"2018-05-09","code":"CZ2018-02（252/211）","address":"崇州市羊马镇泗安村16、17、19、20组（光华大道与羊安路交叉口西北侧）","area":"48996.64\n\n合73.4950亩","areaTrans":"48996.64","type":"住宅兼容商业\n\n住宅70年，商业40年","startPrice":"208万元/亩","startPriceTrans":"3123.12","img":"http://www.cdggzy.com:8080/ueditor/netfile/upload/2018-05-09/2a86e79a-47e2-4657-a23f-149a680fe729.jpg","localImg":"2a86e79a-47e2-4657-a23f-149a680fe729.jpg"},{"url":"http://www.cdlr.gov.cn/detailnoright.aspx?id=115615","title":"成都市拍卖出让国有建设用地使用权公告(成公资土拍告[2018]20号)","date":"2018-05-09","code":"JYS2018-3","address":"简阳市简州新城龙腾大道以东，涟江大道以南，规划支路以西，规划道路以北","area":"55208.91\n\n合82.8134亩","areaTrans":"55208.91","type":"住宅用地\n\n70年","startPrice":"楼面地价：4000元/平方米\n\n ","startPriceTrans":"4000","img":"http://www.cdggzy.com:8080/ueditor/netfile/upload/2018-05-09/31b1780d-5024-4ea8-a369-16a0116e3d3e.jpg","localImg":"31b1780d-5024-4ea8-a369-16a0116e3d3e.jpg"},{"url":"http://www.cdlr.gov.cn/detailnoright.aspx?id=115614","title":"成都市挂牌出让国有建设用地使用权公告(成公资土挂告[2018]22号)","date":"2018-05-09","code":"CZ2017-04（211）","address":"崇州市三郎镇和平社区1、2、3组","area":"101181.73\n\n合151.7726亩","areaTrans":"101181.73","type":"商业用地\n\n40年","startPrice":"66万元/亩","startPriceTrans":"990.99","img":"http://www.cdggzy.com:8080/ueditor/netfile/upload/2018-05-09/b284d975-ec45-40de-b4fe-9f82c0157cd1.jpg","localImg":"b284d975-ec45-40de-b4fe-9f82c0157cd1.jpg"},{"url":"http://www.cdlr.gov.cn/detailnoright.aspx?id=115614","title":"成都市挂牌出让国有建设用地使用权公告(成公资土挂告[2018]22号)","date":"2018-05-09","code":"CZ2017-25（211）","address":"崇州市三郎镇和平社区一、三组","area":"22224.32\n\n合33.3365亩","areaTrans":"22224.32","type":"商业用地\n\n40年","startPrice":"66万元/亩","startPriceTrans":"990.99","localImg":""},{"url":"http://www.cdlr.gov.cn/detailnoright.aspx?id=115614","title":"成都市挂牌出让国有建设用地使用权公告(成公资土挂告[2018]22号)","date":"2018-05-09","code":"CZ2017-27（211）","address":"崇州市三郎镇和平社区一组","area":"7674.65\n\n合11.5120亩","areaTrans":"7674.65","type":"商业用地\n\n40年","startPrice":"66万元/亩","startPriceTrans":"990.99","localImg":""},{"url":"http://www.cdlr.gov.cn/detailnoright.aspx?id=115614","title":"成都市挂牌出让国有建设用地使用权公告(成公资土挂告[2018]22号)","date":"2018-05-09","code":"CZ2017-26（211）","address":"崇州市三郎镇和平社区一、三组","area":"16788.61\n\n合25.1829亩","areaTrans":"16788.61","type":"商业用地\n\n40年","startPrice":"66万元/亩","startPriceTrans":"990.99","localImg":""},{"url":"http://www.cdlr.gov.cn/detailnoright.aspx?id=115239","title":"成都市拍卖出让国有建设用地使用权公告(成公资土拍告[2018]19号)","date":"2018-05-04","code":"CZ2018-01（252/211）","address":"崇州市文井北街东南侧（崇州市崇阳镇棋盘村集体）","area":"14959.65\n\n合22.4395亩","areaTrans":"14959.65","type":"住宅兼容商业\n\n住宅用地70年，商业用地40年","startPrice":"210万元/亩","startPriceTrans":"3153.15","img":"http://www.cdggzy.com:8080/ueditor/netfile/upload/2018-05-04/cf2f664b-da9e-499a-8fc2-aaa3da579235.jpg","localImg":"cf2f664b-da9e-499a-8fc2-aaa3da579235.jpg"}]